AUTHORS
LICENSE
MANIFEST.in
README.rst
setup.py
django_socialregistration.egg-info/PKG-INFO
django_socialregistration.egg-info/SOURCES.txt
django_socialregistration.egg-info/dependency_links.txt
django_socialregistration.egg-info/not-zip-safe
django_socialregistration.egg-info/requires.txt
django_socialregistration.egg-info/top_level.txt
socialregistration/__init__.py
socialregistration/auth.py
socialregistration/forms.py
socialregistration/middleware.py
socialregistration/mixins.py
socialregistration/models.py
socialregistration/settings.py
socialregistration/signals.py
socialregistration/tests.py
socialregistration/urls.py
socialregistration/utils.py
socialregistration/views.py
socialregistration/clients/__init__.py
socialregistration/clients/oauth.py
socialregistration/compat/__init__.py
socialregistration/compat/urls.py
socialregistration/contrib/__init__.py
socialregistration/contrib/facebook/__init__.py
socialregistration/contrib/facebook/admin.py
socialregistration/contrib/facebook/auth.py
socialregistration/contrib/facebook/client.py
socialregistration/contrib/facebook/middleware.py
socialregistration/contrib/facebook/models.py
socialregistration/contrib/facebook/tests.py
socialregistration/contrib/facebook/urls.py
socialregistration/contrib/facebook/views.py
socialregistration/contrib/facebook/templates/socialregistration/facebook/facebook.html
socialregistration/contrib/facebook/templates/socialregistration/facebook/facebook_button.html
socialregistration/contrib/facebook/templatetags/__init__.py
socialregistration/contrib/facebook/templatetags/facebook.py
socialregistration/contrib/facebook/templatetags/facebook_tags.py
socialregistration/contrib/foursquare/__init__.py
socialregistration/contrib/foursquare/admin.py
socialregistration/contrib/foursquare/auth.py
socialregistration/contrib/foursquare/client.py
socialregistration/contrib/foursquare/models.py
socialregistration/contrib/foursquare/tests.py
socialregistration/contrib/foursquare/urls.py
socialregistration/contrib/foursquare/views.py
socialregistration/contrib/foursquare/templates/socialregistration/foursquare/foursquare.html
socialregistration/contrib/foursquare/templates/socialregistration/foursquare/foursquare_button.html
