Metadata-Version: 1.1
Name: django-socialregistration
Version: 0.5.10
Summary: Django app providing registration through a variety of APIs
Home-page: http://github.com/flashingpumpkin/django-socialregistration
Author: Alen Mujezinovic
Author-email: alen@caffeinehit.com
License: UNKNOWN
Keywords: django facebook twitter oauth openid registration foursquare linkedin github oauth2
Platform: UNKNOWN
Classifier: Development Status :: 4 - Beta
Classifier: Intended Audience :: Developers
Classifier: Topic :: Software Development :: Libraries :: Python Modules
Classifier: Environment :: Web Environment
Classifier: Topic :: Internet
Classifier: Operating System :: OS Independent
Classifier: Programming Language :: Python
Classifier: Framework :: Django
